giga_auto/__init__.py
giga_auto/aes_encrypt.py
giga_auto/assert_utils.py
giga_auto/base_class.py
giga_auto/case_operate.py
giga_auto/constants.py
giga_auto/context_manager.py
giga_auto/data_structure.py
giga_auto/date_utils.py
giga_auto/db_utils.py
giga_auto/excel_utils.py
giga_auto/expect_utils.py
giga_auto/file_utils.py
giga_auto/logger.py
giga_auto/random_utils.py
giga_auto/request.py
giga_auto/utils.py
giga_auto/yaml_utils.py
giga_auto/assert_class/__init__.py
giga_auto/assert_class/common_assert.py
giga_auto/assert_class/container_assert.py
giga_auto/assert_class/date_assert.py
giga_auto/assert_class/excel_assert.py
giga_auto/assert_class/string_assert.py
giga_auto/conf/__init__.py
giga_auto/conf/settings.py
giga_auto/config/__init__.py
giga_auto/file_attr/__init__.py
giga_auto/file_attr/excel_attr.py
giga_auto/parse/__init__.py
giga_auto/parse/api_decorate.py
giga_auto/parse/business.py
giga_auto/parse/case_docarate.py
giga_auto/parse/parse_base.py
giga_auto/parse/parse_case.py
giga_auto/parse/parse_common.py
giga_auto/parse/parse_step.py
giga_auto-0.3.39.dist-info/LICENSE
giga_auto-0.3.39.dist-info/METADATA
giga_auto-0.3.39.dist-info/WHEEL
giga_auto-0.3.39.dist-info/top_level.txt
giga_auto-0.3.39.dist-info/RECORD
