Metadata-Version: 2.1
Name: giga_auto
Version: 0.3.39
Summary: giga auto test common package
Home-page: https://github.com/your_username/your_package_name
Author: LangMuQing
Author-email: langli0728@gmail.com
Classifier: Programming Language :: Python :: 3
Classifier: License :: OSI Approved :: MIT License
Classifier: Operating System :: OS Independent
Requires-Python: >=3.7
License-File: LICENSE
